{
  "schemaVersion": 1,
  "id": "fwportals",
  "version": "${mod_version}",
  "name": "Forever World Portals",
  "description": "Pass 0 placeholder scaffold for a server-side portal mod.",
  "authors": ["pcal.net"],
  "contact": {
    "homepage": "https://github.com/pcal43/forever-world-portals",
    "sources": "https://github.com/pcal43/forever-world-portals"
  },
  "license": "MIT",
  "environment": "server",
  "entrypoints": {
    "main": [
      "net.pcal.fwportals.fabric.ForeverWorldPortalsFabricInitializer"
    ]
  },
  "depends": {
    "fabricloader": ">=${fabric_loader_version}",
    "fabric-api": "*",
    "minecraft": ">=${minecraft_version}",
    "java": ">=${java_version}"
  },
  "conflicts": {}
}
